LICENSE.txt
MANIFEST.in
README
README.rst
setup.cfg
setup.py
sara/CLI.py
sara/Sara.py
sara/SubModLoader.py
sara/__init__.py
sara/main.py
sara/templates.py
sara/submodules/BaseConfig.py
sara/submodules/__init__.py
sara/submodules/wxprot.py
saractl.egg-info/PKG-INFO
saractl.egg-info/SOURCES.txt
saractl.egg-info/dependency_links.txt
saractl.egg-info/entry_points.txt
saractl.egg-info/requires.txt
saractl.egg-info/top_level.txt